qat/__init__.py
qat/backend/__init__.py
qat/backend/base.py
qat/backend/codegen_base.py
qat/backend/fallthrough.py
qat/backend/graph.py
qat/backend/passes/__init__.py
qat/backend/passes/analysis.py
qat/backend/passes/lowering.py
qat/backend/passes/purr/__init__.py
qat/backend/passes/purr/analysis.py
qat/backend/passes/purr/lowering.py
qat/backend/passes/purr/transform.py
qat/backend/passes/purr/validation.py
qat/backend/passes/validation.py
qat/backend/qblox/__init__.py
qat/backend/qblox/acquisition.py
qat/backend/qblox/codegen.py
qat/backend/qblox/config/__init__.py
qat/backend/qblox/config/constants.py
qat/backend/qblox/config/helpers.py
qat/backend/qblox/config/specification.py
qat/backend/qblox/execution.py
qat/backend/qblox/ir.py
qat/backend/qblox/passes/__init__.py
qat/backend/qblox/passes/analysis.py
qat/backend/qblox/visualisation.py
qat/backend/waveform/__init__.py
qat/backend/waveform/codegen.py
qat/backend/waveform/executable.py
qat/backend/waveform_v1/__init__.py
qat/backend/waveform_v1/executable.py
qat/backend/waveform_v1/purr/__init__.py
qat/backend/waveform_v1/purr/codegen.py
qat/core/__init__.py
qat/core/config/__init__.py
qat/core/config/configure.py
qat/core/config/descriptions.py
qat/core/config/session.py
qat/core/config/validators.py
qat/core/metrics_base.py
qat/core/pass_base.py
qat/core/pipeline.py
qat/core/pipelines/__init__.py
qat/core/pipelines/configurable.py
qat/core/pipelines/factory.py
qat/core/qat.py
qat/core/result_base.py
qat/engines/__init__.py
qat/engines/model.py
qat/engines/native.py
qat/engines/qblox/__init__.py
qat/engines/qblox/dummy.py
qat/engines/qblox/execution.py
qat/engines/qblox/live.py
qat/engines/waveform/__init__.py
qat/engines/waveform/echo.py
qat/engines/waveform_v1/__init__.py
qat/engines/waveform_v1/echo.py
qat/engines/zero.py
qat/executables.py
qat/extensions.py
qat/frontend/__init__.py
qat/frontend/auto.py
qat/frontend/base.py
qat/frontend/circuit_builder.py
qat/frontend/custom.py
qat/frontend/fallthrough.py
qat_compiler-3.2.1.dist-info/METADATA
qat_compiler-3.2.1.dist-info/WHEEL
qat_compiler-3.2.1.dist-info/entry_points.txt
qat_compiler-3.2.1.dist-info/licenses/LICENSE
qat_compiler-3.2.1.dist-info/RECORD
