Metadata-Version: 2.4
Name: qat-compiler
Version: 3.2.1
Summary: A low-level quantum compiler and runtime which facilitates executing quantum IRs.
License-Expression: BSD-3-Clause
License-File: LICENSE
Author: Hamid El Maazouz
Author-email: helmaazouz@oqc.tech
Requires-Python: >=3.10,<3.13
Classifier: Programming Language :: Python :: 3
Classifier: Programming Language :: Python :: 3.10
Classifier: Programming Language :: Python :: 3.11
Classifier: Programming Language :: Python :: 3.12
Requires-Dist: compiler-config (>=0.2.0,<0.3.0)
Requires-Dist: frozendict (>=2.4.6,<3.0.0)
Requires-Dist: jsonpickle (>=4.0.5)
Requires-Dist: lark-parser (>=0.12.0,<0.13.0)
Requires-Dist: logging-config (>=1.0.4,<2.0.0)
Requires-Dist: matplotlib (>=3.7.5,<4.0.0)
Requires-Dist: more-itertools (>=10.7.0,<11.0.0)
Requires-Dist: networkx (>=2.5)
Requires-Dist: numpy (>=1.26.4)
Requires-Dist: numpydantic (>=1.6.7)
Requires-Dist: openqasm3[parser] (>=1.0.0,<2.0.0)
Requires-Dist: piny (>=1.1.0,<2.0.0)
Requires-Dist: pydantic (==2.11.7)
Requires-Dist: pydantic-extra-types (>=2.10.4,<3.0.0)
Requires-Dist: pydantic-settings (>=2.5.2)
Requires-Dist: pyqir (>=0.11.0,!=0.12.0,!=0.12.1,!=0.12.2,<0.13.0)
Requires-Dist: pytket (>=1.41.0,<2.0.0)
Requires-Dist: qblox-instruments (==0.17.1)
Requires-Dist: qiskit (>=1.4.2,<3.0.0)
Requires-Dist: qiskit-aer (>=0.17.1,<0.18.0)
Requires-Dist: qiskit-experiments (>=0.11.0,<0.12.0)
Requires-Dist: qutip (>=5.2.0)
Requires-Dist: regex (>=3.6.1)
Requires-Dist: scipy (>=1.15.2)
Requires-Dist: semver (>=3.0.2,<4.0.0)
Requires-Dist: sympy (>=1.14.0,<2.0.0)
Requires-Dist: toml (>=0.10.2,<0.11.0)
Project-URL: Documentation, https://oqc-community.github.io/qat/main/index.html
Project-URL: Homepage, https://oqc.tech/
Project-URL: Repository, https://github.com/oqc-community/qat
